ifsm/__init__.py
ifsm/core.py
ifsm-1.1.dist-info/LICENSE
ifsm-1.1.dist-info/METADATA
ifsm-1.1.dist-info/WHEEL
ifsm-1.1.dist-info/top_level.txt
ifsm-1.1.dist-info/RECORD
